clamd/__init__.py
python_mollusc-1.0.3.dist-info/METADATA
python_mollusc-1.0.3.dist-info/WHEEL
python_mollusc-1.0.3.dist-info/top_level.txt
python_mollusc-1.0.3.dist-info/zip-safe
python_mollusc-1.0.3.dist-info/RECORD
