Metadata-Version: 2.1
Name: python-mollusc
Version: 1.0.3
Summary: Python clamd client (fork of python-clamd)
Home-page: https://github.com/chowchow1/python-mollusc
Author: chowchow1
License: UNKNOWN
Keywords: python,clamav,antivirus,scanner,virus,libclamav,clamd
Platform: UNKNOWN
Classifier: License :: OSI Approved :: GNU Library or Lesser General Public License (LGPL)
